pxr/.libs/libPxrKind.so
pxr/Kind/__init__.py
pxr/Kind/_kind.so
pxr_kind-25.8.dist-info/METADATA
pxr_kind-25.8.dist-info/WHEEL
pxr_kind-25.8.dist-info/RECORD
pxr_kind-25.8.dist-info/licenses/LICENSE.txt
pxr_kind-25.8.dist-info/licenses/NOTICE.txt
